{"_id":{"$oid":"6845dc12b3df2300076fe964"},"topic":"module/v1/ff/DRILL001/state","payload":{"headerId":2,"loads":[],"actionState":{"id":"action-0001","command":"PICK","metadata":{"type":"BLUE"},"state":"RUNNING"},"serialNumber":"DRILL001","timestamp":"2025-06-08T18:53:06.484Z","errors":[],"orderUpdateId":0,"orderId":"0","paused":false,"metadata":{"opcuaState":"connected"},"moduleState":"PICKBUSY"},"qos":1,"retain":false,"_msgid":"7fcb46be140ee157"}
{"_id":{"$oid":"6845dc2ab3df2300076fe965"},"topic":"module/v1/ff/DRILL001/state","payload":{"headerId":3,"loads":[],"actionState":{"id":"action-0001","command":"PICK","metadata":{"type":"BLUE"},"state":"FINISHED"},"serialNumber":"DRILL001","timestamp":"2025-06-08T18:53:30.148Z","errors":[],"orderUpdateId":2,"orderId":"0","paused":false,"metadata":{"opcuaState":"connected"},"moduleState":"WAITING_AFTER_PICK"},"qos":1,"retain":false,"_msgid":"af41c047d62ca0e8"}
{"_id":{"$oid":"6845dc2ab3df2300076fe966"},"topic":"module/v1/ff/DRILL001/state","payload":{"headerId":4,"loads":[],"actionState":{"id":"action-0002","command":"DRILL","metadata":{"duration":20,"type":"BLUE"},"state":"RUNNING"},"serialNumber":"DRILL001","timestamp":"2025-06-08T18:53:30.157Z","errors":[],"orderUpdateId":2,"orderId":"0","paused":false,"metadata":{"opcuaState":"connected"},"moduleState":"DRILLBUSY"},"qos":1,"retain":false,"_msgid":"47497e3b65e0c548"}
{"_id":{"$oid":"6845dc35b3df2300076fe967"},"topic":"module/v1/ff/DRILL001/state","payload":{"headerId":5,"loads":[],"actionState":{"id":"action-0002","command":"DRILL","metadata":{"duration":20,"type":"BLUE"},"state":"FINISHED"},"serialNumber":"DRILL001","timestamp":"2025-06-08T18:53:41.148Z","errors":[],"orderUpdateId":2,"orderId":"0","paused":false,"metadata":{"opcuaState":"connected"},"moduleState":"WAITING_AFTER_DRILL"},"qos":1,"retain":false,"_msgid":"c4f8694ab4f45604"}
{"_id":{"$oid":"6845dc35b3df2300076fe968"},"topic":"module/v1/ff/DRILL001/state","payload":{"headerId":6,"loads":[],"actionState":{"id":"action-0003","command":"DROP","state":"RUNNING"},"serialNumber":"DRILL001","timestamp":"2025-06-08T18:53:41.154Z","errors":[],"orderUpdateId":2,"orderId":"0","paused":false,"metadata":{"opcuaState":"connected"},"moduleState":"DROPBUSY"},"qos":1,"retain":false,"_msgid":"44e0b9bbc1f2cdd4"}
{"_id":{"$oid":"6845dc4eb3df2300076fe969"},"topic":"module/v1/ff/DRILL001/state","payload":{"headerId":7,"loads":[],"actionState":{"id":"action-0003","command":"DROP","state":"FINISHED"},"serialNumber":"DRILL001","timestamp":"2025-06-08T18:54:06.149Z","errors":[],"orderUpdateId":2,"orderId":"0","paused":false,"metadata":{"opcuaState":"connected"},"moduleState":"IDLE"},"qos":1,"retain":false,"_msgid":"5fba24b428154c30"}
{"_id":{"$oid":"684620a525a93b00088650e7"},"topic":"module/v1/ff/DRILL001/state","payload":{"headerId":0,"loads":[],"actionState":null,"serialNumber":"DRILL001","timestamp":"2025-06-08T23:45:41.440Z","errors":[],"orderUpdateId":0,"orderId":"","paused":false,"metadata":{"opcuaState":"connected"}},"qos":1,"retain":false,"_msgid":"0492444d91a4d8fb"}
{"_id":{"$oid":"68462f5b25a93b00088650f6"},"topic":"module/v1/ff/DRILL001/state","payload":{"headerId":2,"loads":[],"actionState":{"id":"action-0001","command":"PICK","metadata":{"type":"BLUE"},"state":"RUNNING"},"serialNumber":"DRILL001","timestamp":"2025-06-09T00:48:27.727Z","errors":[],"orderUpdateId":0,"orderId":"0","paused":false,"metadata":{"opcuaState":"connected"},"moduleState":"PICKBUSY"},"qos":1,"retain":false,"_msgid":"cb8627a6ffa96298"}
{"_id":{"$oid":"68462f7325a93b00088650f7"},"topic":"module/v1/ff/DRILL001/state","payload":{"headerId":3,"loads":[],"actionState":{"id":"action-0001","command":"PICK","metadata":{"type":"BLUE"},"state":"FINISHED"},"serialNumber":"DRILL001","timestamp":"2025-06-09T00:48:51.562Z","errors":[],"orderUpdateId":2,"orderId":"0","paused":false,"metadata":{"opcuaState":"connected"},"moduleState":"WAITING_AFTER_PICK"},"qos":1,"retain":false,"_msgid":"ab5d01487da1b0ad"}
{"_id":{"$oid":"68462f7325a93b00088650f8"},"topic":"module/v1/ff/DRILL001/state","payload":{"headerId":4,"loads":[],"actionState":{"id":"action-0002","command":"DRILL","metadata":{"duration":20,"type":"BLUE"},"state":"RUNNING"},"serialNumber":"DRILL001","timestamp":"2025-06-09T00:48:51.570Z","errors":[],"orderUpdateId":2,"orderId":"0","paused":false,"metadata":{"opcuaState":"connected"},"moduleState":"DRILLBUSY"},"qos":1,"retain":false,"_msgid":"745981fb2cd4ccfc"}
{"_id":{"$oid":"68462f7e25a93b00088650f9"},"topic":"module/v1/ff/DRILL001/state","payload":{"headerId":5,"loads":[],"actionState":{"id":"action-0002","command":"DRILL","metadata":{"duration":20,"type":"BLUE"},"state":"FINISHED"},"serialNumber":"DRILL001","timestamp":"2025-06-09T00:49:02.563Z","errors":[],"orderUpdateId":2,"orderId":"0","paused":false,"metadata":{"opcuaState":"connected"},"moduleState":"WAITING_AFTER_DRILL"},"qos":1,"retain":false,"_msgid":"fb85b2875fddb064"}
{"_id":{"$oid":"68462f7e25a93b00088650fa"},"topic":"module/v1/ff/DRILL001/state","payload":{"headerId":6,"loads":[],"actionState":{"id":"action-0003","command":"DROP","state":"RUNNING"},"serialNumber":"DRILL001","timestamp":"2025-06-09T00:49:02.569Z","errors":[],"orderUpdateId":2,"orderId":"0","paused":false,"metadata":{"opcuaState":"connected"},"moduleState":"DROPBUSY"},"qos":1,"retain":false,"_msgid":"66635b5d7596a0fe"}
{"_id":{"$oid":"68462f9725a93b00088650fb"},"topic":"module/v1/ff/DRILL001/state","payload":{"headerId":7,"loads":[],"actionState":{"id":"action-0003","command":"DROP","state":"FINISHED"},"serialNumber":"DRILL001","timestamp":"2025-06-09T00:49:27.564Z","errors":[],"orderUpdateId":2,"orderId":"0","paused":false,"metadata":{"opcuaState":"connected"},"moduleState":"IDLE"},"qos":1,"retain":false,"_msgid":"9521e267973c1293"}
